buntstrap/__init__.py
buntstrap/__main__.py
buntstrap/chroot.py
buntstrap/config.py
buntstrap/freeze.py
buntstrap/size_report.py
buntstrap/util.py
buntstrap-0.1.5.dist-info/METADATA
buntstrap-0.1.5.dist-info/WHEEL
buntstrap-0.1.5.dist-info/entry_points.txt
buntstrap-0.1.5.dist-info/top_level.txt
buntstrap-0.1.5.dist-info/RECORD
