Metadata-Version: 2.1
Name: buntstrap
Version: 0.1.5
Summary: bootstrap an ubuntu filesystem
Home-page: https://github.com/cheshirekow/buntstrap
Author: Josh Bialkowski
Author-email: josh.bialkowski@gmail.com
License: UNKNOWN
Download-URL: https://github.com/cheshirekow/buntstrap/archive/0.1.5.tar.gz
Keywords: ubuntu,linux
Platform: UNKNOWN
Requires-Dist: uchroot
